<xml xmlns="http://www.w3.org/1999/xhtml"><block type="onfirstboot" id="onfirstboot" x="0" y="0"><next><block type="wifisetup" id="H{hAO;}Hjy:.~zgtk7p?"><field name="1">network-name</field><field name="2">network-password</field><field name="3">WPA/WPA2</field><next><block type="sethostname" id="kv5@ihl@JSKZs.^2M`vL"><field name="1">pibeacon</field><next><block type="runcommand" id="mpbnc/_~[kAi2tq=3#k|"><field name="1">mkdir /home/pi/PiBeacon/</field><field name="2">pi</field><next><block type="downloadfile" id="zV1U/;bKxkX}0.FV;GR~"><field name="1">https://github.com/Gerzer/PiBeacon/raw/master/Beacon.py</field><field name="2">/home/pi/PiBeacon/Beacon.py</field><next><block type="runcommand" id="LznIG_^xMl!Vzj]7_s5d"><field name="1">echo -n "00 00" &gt; /home/pi/PiBeacon/Major.txt</field><field name="2">pi</field><next><block type="runcommand" id="5vYc4~5sN,Gh|O0~G/h?"><field name="1">echo -n "00 00" &gt; /home/pi/PiBeacon/Minor.txt</field><field name="2">pi</field><next><block type="bootbehaviour" id="en2MN|{i(O:u(t.0`SD@"><field name="1">Console logged in</field><next><block type="reboot" id="l+C|{P)*oHvG_7ib94g;"></block></next></block></next></block></next></block></next></block></next></block></next></block></next></block></next></block><block type="onboot" id="idO]|M@E+;eP2Md0)Gc4" x="0" y="482"><next><block type="runpython" id="|SBiMN2FP|Tzvjf,7F6k"><field name="1">/home/pi/PiBeacon/Beacon.py</field><field name="2">root</field></block></next></block></xml>